collective.z3cform.colorpicker-3.0.1-py3.11-nspkg.pth
collective/z3cform/colorpicker/__init__.py
collective/z3cform/colorpicker/colorpicker.py
collective/z3cform/colorpicker/colorpicker_display.pt
collective/z3cform/colorpicker/colorpicker_input.pt
collective/z3cform/colorpicker/configure.zcml
collective/z3cform/colorpicker/fields.py
collective/z3cform/colorpicker/demo/__init__.py
collective/z3cform/colorpicker/demo/browser.py
collective/z3cform/colorpicker/demo/configure.zcml
collective/z3cform/colorpicker/locales/collective.z3cform.colorpicker.pot
collective/z3cform/colorpicker/locales/rebuild.sh
collective/z3cform/colorpicker/locales/es/LC_MESSAGES/collective.z3cform.colorpicker.mo
collective/z3cform/colorpicker/locales/es/LC_MESSAGES/collective.z3cform.colorpicker.po
collective/z3cform/colorpicker/locales/it/LC_MESSAGES/collective.z3cform.colorpicker.mo
collective/z3cform/colorpicker/locales/it/LC_MESSAGES/collective.z3cform.colorpicker.po
collective/z3cform/colorpicker/locales/nl/LC_MESSAGES/collective.z3cform.colorpicker.mo
collective/z3cform/colorpicker/locales/nl/LC_MESSAGES/collective.z3cform.colorpicker.po
collective/z3cform/colorpicker/profiles/default/metadata.xml
collective/z3cform/colorpicker/profiles/default/registry/.gitkeep
collective.z3cform.colorpicker-3.0.1.dist-info/METADATA
collective.z3cform.colorpicker-3.0.1.dist-info/WHEEL
collective.z3cform.colorpicker-3.0.1.dist-info/entry_points.txt
collective.z3cform.colorpicker-3.0.1.dist-info/namespace_packages.txt
collective.z3cform.colorpicker-3.0.1.dist-info/top_level.txt
collective.z3cform.colorpicker-3.0.1.dist-info/RECORD
