Metadata-Version: 2.1
Name: collective.z3cform.colorpicker
Version: 3.0.1
Summary: Colorpicker widget for Plone
Home-page: http://www.giorgioborelli.it
Author: Giorgio Borelli
Author-email: giorgio@giorgioborelli.it
License: GPL
Keywords: plone z3cform colorpicker widget
Classifier: Development Status :: 5 - Production/Stable
Classifier: Environment :: Web Environment
Classifier: Framework :: Plone
Classifier: Framework :: Plone :: 6.0
Classifier: Intended Audience :: End Users/Desktop
Classifier: License :: OSI Approved :: GNU General Public License v2 (GPLv2)
Classifier: Operating System :: OS Independent
Classifier: Programming Language :: Python
Classifier: Programming Language :: Python :: 3.8
Classifier: Programming Language :: Python :: 3.9
Classifier: Programming Language :: Python :: 3.10
Classifier: Topic :: Internet
Classifier: Topic :: Software Development :: Libraries :: Python Modules
Requires-Dist: setuptools
Requires-Dist: Products.CMFCore
Requires-Dist: plone.app.z3cform
